commitizen/__init__.py
commitizen/__main__.py
commitizen/__version__.py
commitizen/bump.py
commitizen/changelog.py
commitizen/changelog_formats/__init__.py
commitizen/changelog_formats/asciidoc.py
commitizen/changelog_formats/base.py
commitizen/changelog_formats/markdown.py
commitizen/changelog_formats/restructuredtext.py
commitizen/changelog_formats/textile.py
commitizen/cli.py
commitizen/cmd.py
commitizen/commands/__init__.py
commitizen/commands/bump.py
commitizen/commands/changelog.py
commitizen/commands/check.py
commitizen/commands/commit.py
commitizen/commands/example.py
commitizen/commands/info.py
commitizen/commands/init.py
commitizen/commands/list_cz.py
commitizen/commands/schema.py
commitizen/commands/version.py
commitizen/config/__init__.py
commitizen/config/base_config.py
commitizen/config/factory.py
commitizen/config/json_config.py
commitizen/config/toml_config.py
commitizen/config/yaml_config.py
commitizen/cz/__init__.py
commitizen/cz/base.py
commitizen/cz/conventional_commits/__init__.py
commitizen/cz/conventional_commits/conventional_commits.py
commitizen/cz/conventional_commits/conventional_commits_info.txt
commitizen/cz/customize/__init__.py
commitizen/cz/customize/customize.py
commitizen/cz/customize/customize_info.txt
commitizen/cz/exceptions.py
commitizen/cz/jira/__init__.py
commitizen/cz/jira/jira.py
commitizen/cz/jira/jira_info.txt
commitizen/cz/utils.py
commitizen/defaults.py
commitizen/exceptions.py
commitizen/factory.py
commitizen/git.py
commitizen/hooks.py
commitizen/out.py
commitizen/project_info.py
commitizen/providers/__init__.py
commitizen/providers/base_provider.py
commitizen/providers/cargo_provider.py
commitizen/providers/commitizen_provider.py
commitizen/providers/composer_provider.py
commitizen/providers/npm_provider.py
commitizen/providers/pep621_provider.py
commitizen/providers/poetry_provider.py
commitizen/providers/scm_provider.py
commitizen/providers/uv_provider.py
commitizen/py.typed
commitizen/question.py
commitizen/tags.py
commitizen-4.13.0.dist-info/WHEEL
commitizen-4.13.0.dist-info/entry_points.txt
commitizen-4.13.0.dist-info/METADATA
commitizen-4.13.0.dist-info/RECORD
