Metadata-Version: 2.3
Name: commitizen
Version: 4.13.0
Summary: Python commitizen client tool
Keywords: commitizen,conventional,commits,git
Author: Santiago Fraire
Author-email: Santiago Fraire <santiwilly@gmail.com>
License: MIT License
Classifier: Development Status :: 5 - Production/Stable
Classifier: Environment :: Console
Classifier: Intended Audience :: Developers
Classifier: Natural Language :: English
Classifier: Operating System :: OS Independent
Classifier: Programming Language :: Python
Classifier: Programming Language :: Python :: 3
Classifier: Programming Language :: Python :: 3.10
Classifier: Programming Language :: Python :: 3.11
Classifier: Programming Language :: Python :: 3.12
Classifier: Programming Language :: Python :: 3.13
Classifier: Programming Language :: Python :: 3.14
Classifier: Programming Language :: Python :: Implementation :: CPython
Classifier: License :: OSI Approved :: MIT License
Requires-Dist: questionary>=2.0,<3.0
Requires-Dist: prompt-toolkit!=3.0.52
Requires-Dist: decli>=0.6.0,<1.0
Requires-Dist: colorama>=0.4.1,<1.0
Requires-Dist: termcolor>=1.1.0,<4.0.0
Requires-Dist: packaging>=19
Requires-Dist: tomlkit>=0.8.0,<1.0.0
Requires-Dist: jinja2>=2.10.3
Requires-Dist: pyyaml>=3.8
Requires-Dist: argcomplete>=1.12.1,<3.7
Requires-Dist: typing-extensions>=4.0.1,<5.0.0 ; python_full_version < '3.11'
Requires-Dist: charset-normalizer>=2.1.0,<4
Requires-Dist: deprecated>=1.2.13,<2
Requires-Dist: importlib-metadata>=8.0.0,<8.7.0 ; python_full_version < '3.10'
Maintainer: Wei Lee, Axel H., Tim Hsiung
Maintainer-email: Wei Lee <weilee.rx@gmail.com>, Axel H. <noirbizarre@gmail.com>, Tim Hsiung <bear890707@gmail.com>
Requires-Python: >=3.10, <4.0
Project-URL: Homepage, https://github.com/commitizen-tools/commitizen
Project-URL: Documentation, https://commitizen-tools.github.io/commitizen/
Project-URL: Repository, https://github.com/commitizen-tools/commitizen
Project-URL: Issues, https://github.com/commitizen-tools/commitizen/issues
Project-URL: Changelog, https://github.com/commitizen-tools/commitizen/blob/master/CHANGELOG.md
